snowflakecopycommand/__init__.py
snowflakecopycommand/bases.py
snowflakecopycommand/copy_command.py
snowflakecopycommand/copy_options.py
snowflakecopycommand/enums.py
snowflakecopycommand/exceptions.py
snowflakecopycommand/file_format.py
snowflakecopycommand/locations.py
snowflakecopycommand/table.py
snowflakecopycommand-0.0.3.dist-info/WHEEL
snowflakecopycommand-0.0.3.dist-info/METADATA
snowflakecopycommand-0.0.3.dist-info/RECORD
