Metadata-Version: 2.1
Name: snowflakecopycommand
Version: 0.0.3
Summary: https://github.com/J-T-R/SnowflakeCopyCommand
Author: Jo
Author-email: jthickpennyryan@gmail.com
Requires-Python: >=3.10
Classifier: Programming Language :: Python :: 3
Classifier: Programming Language :: Python :: 3.10
